{
  "nombre": "Río Camarones en Conanoxa",
  "bna": "01502002-4",
  "tipo": "fluviometrica",
  "variable": "Caudal máximo instantáneo anual",
  "unidad": "m3/s",
  "area_km2": 2009,
  "altitud_m": 710,
  "utm_e": 396224,
  "utm_n": 7893581,
  "cuenca": "15 - Río Camarones",
  "estado": "Vigente",
  "fuente": "DGA - Altura y Caudal Instantáneo Diario (informe S17, Tabla 3-34)",
  "rango_pp_mm_ano": [10, 300],
  "serie": {
    "1968": 1.56, "1969": 3.30, "1970": 2.07, "1971": 3.05,
    "1981": 4.60, "1982": 1.85, "1983": 14.00, "1984": 42.34,
    "1985": 35.48, "1986": 20.62, "1987": 3.94, "1988": 4.33,
    "1989": 49.64, "1990": 38.00, "1991": 38.17, "1992": 11.52,
    "1993": 42.26, "1995": 14.84, "1996": 0.50, "1997": 89.47,
    "1998": 84.22, "2003": 0.89, "2004": 42.70, "2005": 19.87,
    "2006": 6.43, "2007": 23.42, "2008": 41.76, "2009": 6.12,
    "2010": 0.72, "2011": 20.68, "2012": 224.17, "2013": 18.00,
    "2014": 2.30, "2015": 62.08, "2016": 95.87, "2017": 10.49,
    "2018": 5.15, "2019": 0.73
  }
}
